{
    "instance_features": {
        "./external-assets/problem-instances/planning-instances/ipc-2014-learning/elevators/problems-training/ipc-2014-learning-elevators-training-48_65_1.pddl": {
            "MpSAT-gsat_FirstLocalMinStep_CoeffVariance": 0.000000000,
            "MpSAT-VCG-VAR-max": 0.001868598,
            "sasCenamorCGMaxIncomingEdgesPerVariable": 66,
            "MpSAT-DIAMETER-coeff-variation": 0.000000000,
            "sasTranslatorVariables": 97,
            "MpSAT-VCG-CLAUSE-min": 0.000005603,
            "MpSAT-HORNY-VAR-max": 0.001866973,
            "pddlNumActions": 6,
            "sasCenamorCGNumEdges": 3136,
            "pddlRequiresDomainAxioms": 0.0,
            "pddlRequiresContinuousEffects": 0.0,
            "MpSAT-SP-bias-q90": 0.970876149,
            "MpSAT-SP-unconstraint-mean": 0.151538337,
            "sasFileVersion": 3,
            "MpSAT-nvarsOrig": 2078835.000000000,
            "pddlRequiresNegativePreconditions": 0.0,
            "sasImpliedPreconditionsAdded": 0,
            "sasRelevantAtoms": 104544,
            "pddlMeanNegationsPerEffect": 1.33333333333,
            "pddlNumConstantsAndObjects": 130,
            "sasCenamorCGStddevOutgoingEdgeWeightSumPerVariable": 4531.60478846,
            "MpSAT-cluster-coeff-min": -1.000000000,
            "MpSAT-cl-num-q10": 0.000000000,
            "fdProbingFinalHeuristicNum": -512.0,
            "MpSAT-gsat_FirstLocalMinRatio_CoeffVariance": 0.506501000,
            "MpSAT-saps_FirstLocalMinStep_Mean": 0.000000000,
            "sasCenamorCGStddevIncomingEdgesPerHighLevelVariable": 0.0,
            "MpSAT-cl-num-q75": 0.000000000,
            "sasCenamorCGRatioSumOfWeightsToTotalEdges": 123.367346939,
            "MpSAT-VG-max": 0.002464518,
            "sasPreprocessingPercentageOperatorsDeemedNecessary": 1.0,
            "MpSAT-VG-coeff-variation": 1.072513393,
            "MpSAT-CG-max": 0.000000000,
            "MpSAT-cl-size-max": 0.000000000,
            "MpSAT-SP-unconstraint-coeff-variation": 0.710994160,
            "pddlMeanPredicatesPerEffect": 2.66666666667,
            "MpSAT-SP-unconstraint-max": 0.656324069,
            "sasCenamorCGMeanOutgoingEdgesPerVariable": 32.3298969072,
            "MpSAT-cl-num-q25": 0.000000000,
            "MpSAT-SP-unconstraint-min": -0.000000000,
            "pddlNumConstants": 0,
            "meta-time-MpSAT-DIAMETER-featuretime": 2.030000000,
            "sasCenamorDTGMaxIncomingEdgeWeightSumPerVertex": 948.0,
            "MpSAT-TRINARY+": 0.988828223,
            "MpSAT-cluster-coeff-entropy": -0.000000000,
            "sasCenamorCGMaxIncomingEdgeWeightSumPerHighLevelVariable": 2976.0,
            "MpSAT-SP-unconstraint-q50": 0.120430009,
            "MpSAT-cl-size-q50": 0.000000000,
            "MpSAT-SP-bias-q10": 0.574302666,
            "sasUncoveredFacts": 0,
            "MpSAT-POSNEG-RATIO-VAR-entropy": 1.548570875,
            "MpSAT-POSNEG-RATIO-VAR-min": 0.000000000,
            "MpSAT-VCG-CLAUSE-coeff-variation": 5.111988546,
            "MpSAT-cl-num-q50": 0.000000000,
            "MpSAT-DIAMETER-min": 14.000000000,
            "fdProbingLandmarksPercentageDisjunctive": -512.0,
            "MpSAT-SP-bias-min": 0.000000000,
            "torchlight-successPercentage": -512.0,
            "torchlight-deadEndPercentage": -512.0,
            "meta-time-simple-pddl": 0.0360329151154,
            "MpSAT-SP-bias-max": 1.000000000,
            "MpSAT-saps_BestSolution_Mean": 458510.000000000,
            "meta-time-MpSAT": 1198.69425893,
            "sasFileNumOperators": 98208,
            "lpgProbingNumFactsIndividual": -512.0,
            "MpSAT-saps_BestSolution_CoeffVariance": 0.000000000,
            "fdProbingLandmarksPercentageConjunctive": -512.0,
            "sasPropositionsRemoved": 97,
            "pddlRequiresStrips": 0.0,
            "MpSAT-gsat_FirstLocalMinRatio_Mean": 1.781680000,
            "fdProbingFinalStatesEvaluated": -512.0,
            "pddlRequiresDurativeActions": 0.0,
            "sasCenamorDTGTotalNumberOfVertices": 4473.0,
            "meta-time-MpSAT-cl-featuretime": 2.000000000,
            "MpSAT-SP-unconstraint-q25": 0.065143906,
            "sasCenamorCGMaxOutgoingEdgesPerVariable": 66,
            "MpSAT-gsat_BestAvgImprovement_CoeffVariance": 0.539315000,
            "sasFileHasMetric": 1,
            "sasCenamorTotalNumVariables": 97,
            "MpSAT-POSNEG-RATIO-VAR-mean": 0.303247287,
            "fdProbingLandmarksDiscovered": -512.0,
            "MpSAT-CG-entropy": -512.000000000,
            "sasCenamorCGRatioTotalVariablesToTotalEdges": 0.030931122449,
            "meta-time-torchlight": 26.1410241127,
            "sasCenamorCGStddevOutgoingEdgesPerVariable": 23.3963679738,
            "pddlRatioActionsWithNegativeEffectsOverActions": 1.0,
            "MpSAT-POSNEG-RATIO-CLAUSE-mean": 0.397452079,
            "pddlMaxPredicatesPerEffect": 4,
            "sasFileMeanVariableDomainSize": 46.1134020619,
            "sasFileMeanConditionsPerAxiom": -512.0,
            "meta-success-MpSAT": 1,
            "sasTranslatorFacts": 4473,
            "lpgProbingNumFacts": -512.0,
            "torchlight-reachabilityActions": -512.0,
            "MpSAT-SP-unconstraint-q90": 0.300204707,
            "pddlRequiresFluents": 0.0,
            "sasCenamorDTGStddevIncomingEdgeWeightSumPerVertex": 53.4515127488,
            "sasCenamorCGMaxIncomingEdgesPerHighLevelVariable": 32,
            "sasCenamorCGMeanIncomingEdgeWeightSumPerHighLevelVariable": 2976.0,
            "pddlRequiresExistentialPreconditions": 0.0,
            "MpSAT-saps_FirstLocalMinStep_Median": 0.000000000,
            "MpSAT-VCG-CLAUSE-entropy": 0.095956220,
            "MpSAT-POSNEG-RATIO-VAR-max": 1.000000000,
            "MpSAT-HORNY-VAR-entropy": 1.591152417,
            "MpSAT-SP-bias-q50": 0.887116819,
            "fdProbingInitialHeuristicNum": -512.0,
            "sasTranslatorTaskSize": 593892,
            "sasCenamorDTGStddevOutgoingEdgeWeightSumPerVertex": 53.4515127488,
            "sasCenamorDTGMaxIncomingEdgesPerVertex": 1690,
            "MpSAT-nclausesOrig": 11127478.000000000,
            "sasAuxiliaryAtoms": 39761,
            "sasCenamorDTGStddevIncomingEdgesPerVertex": 113.702184452,
            "MpSAT-saps_FirstLocalMinStep_Q.90": 0.000000000,
            "MpSAT-nvars": 356957.000000000,
            "MpSAT-cl-size-coeff-variation": 0.000000000,
            "sasCenamorCGRatioSumOfWeightsToTotalVariables": 3988.45360825,
            "MpSAT-lobjois-log-num-nodes-over-vars": 0.504863093,
            "torchlight-easyActionTemplates": -512.0,
            "pddlHasTypes": 1,
            "pddlRequiresNegation": 0.0,
            "sasFileMinConditionsPerAxiom": -512.0,
            "pddlMinParamsPerPredicate": 2,
            "sasCenamorDTGMeanIncomingEdgesPerVertex": 43.5788061704,
            "sasFileNumGoalPairs": 65,
            "MpSAT-cluster-coeff-coeff-variation": -0.000000000,
            "MpSAT-SP-bias-q75": 0.942650234,
            "pddlRequiresDurationInequalities": 0.0,
            "meta-time-MpSAT-sp-featuretime": 27.650000000,
            "MpSAT-HORNY-VAR-mean": 0.000005540,
            "MpSAT-VCG-CLAUSE-max": 0.004740067,
            "sasFileMaxConditionsPerAxiom": -512.0,
            "MpSAT-cl-size-q90": 0.000000000,
            "sasFileMaxPrevailConditionsPerOperator": 1,
            "sasFileMinPrevailConditionsPerOperator": 0,
            "pddlRequiresQuantifiedPreconditions": 0.0,
            "MpSAT-POSNEG-RATIO-CLAUSE-entropy": 0.753972709,
            "sasCenamorCGMaxOutgoingEdgeWeightSumPerVariable": 20280,
            "lpgProbingNumConditionalActions": -512.0,
            "MpSAT-VCG-VAR-min": 0.000000812,
            "pddlNumEqualityInitialConditions": 130,
            "pddlMaxPredicatesPerPrecondition": 5,
            "MpSAT-CG-coeff-variation": -0.000000000,
            "pddlRequiresTimedInitialLiterals": 0.0,
            "MpSAT-cl-size-mean": 0.000000000,
            "sasPreprocessingNumFacts": 4473,
            "torchlight-exitDistanceMin": -512.0,
            "sasPreprocessingDerivedVariables": 0,
            "MpSAT-cl-num-q90": 0.000000000,
            "torchlight-exitDistanceMax": -512.0,
            "MpSAT-cl-num-max": 0.000000000,
            "MpSAT-saps_BestAvgImprovement_CoeffVariance": 0.000000000,
            "meta-time-MpSAT-ls-saps-featuretime": 3.430000000,
            "MpSAT-HORNY-VAR-coeff-variation": 4.969626959,
            "sasFileMaxVariableDomainSize": 65,
            "MpSAT-gsat_FirstLocalMinStep_Q.10": 0.000000000,
            "MpSAT-VCG-VAR-mean": 0.000006696,
            "pddlRequiresConditionalEffects": 0.0,
            "sasCenamorCGStddevIncomingEdgeWeightSumPerHighLevelVariable": 0.0,
            "fdProbingPercentageImprovementNum": -512.0,
            "MpSAT-cl-num-coeff-variation": 0.000000000,
            "MpSAT-POSNEG-RATIO-CLAUSE-min": 0.000000000,
            "sasCenamorDTGMeanIncomingEdgeWeightSumPerVertex": 9.56136820926,
            "MpSAT-cl-size-q25": 0.000000000,
            "pddlRequiresEquality": 0.0,
            "meta-time-MpSAT-CG-featuretime": 20.150000000,
            "MpSAT-saps_FirstLocalMinRatio_CoeffVariance": 0.000000000,
            "sasPreprocessingPercentageMutexGroupsDeemedNecessary": 0.0,
            "sasCenamorCGMaxIncomingEdgeWeightSumPerVariable": 20280,
            "fdProbingReasonableOrdersRemoved": -512.0,
            "fdProbingInitialHeuristicDen": -512.0,
            "MpSAT-UNARY": 0.000000000,
            "meta-success-simple-pddl": 1,
            "meta-time-MpSAT-KLB-featuretime": 312.330000000,
            "MpSAT-VCG-CLAUSE-mean": 0.000006696,
            "fdProbingFinalHeuristicDen": -512.0,
            "fdProbingInitialLandmarks": -512.0,
            "pddlRequiresNumericFluents": 0.0,
            "sasCenamorCGStddevIncomingEdgesPerVariable": 19.0584198636,
            "meta-time-lpg-probing": 0.138612031937,
            "sasFileMeanPrevailConditionsPerOperator": 0.984848484848,
            "meta-time-MpSAT-lobjois-featuretime": 2.120000000,
            "MpSAT-gsat_FirstLocalMinStep_Mean": 0.000000000,
            "pddlRequiresDisjunctivePreconditions": 0.0,
            "MpSAT-vars-clauses-ratio": 0.145001968,
            "sasTranslatorTotalMutexGroupsSize": 4473,
            "MpSAT-VG-min": 0.000000812,
            "MpSAT-HORNY-VAR-min": 0.000000812,
            "MpSAT-gsat_BestSolution_CoeffVariance": 0.914252000,
            "sasEffectConditionsSimplified": 0,
            "pddlNumFunctionAssignmentsInInitialConditions": 295,
            "MpSAT-saps_FirstLocalMinRatio_Mean": 4.132390000,
            "pddlRequiresUniversalPreconditions": 0.0,
            "MpSAT-gsat_FirstLocalMinStep_Q.90": 0.000000000,
            "sasCenamorDTGSumOfEdgeWeights": 42768.0,
            "pddlMinPredicatesPerPrecondition": 3,
            "meta-time-sas": 38.2359240055,
            "pddlRequiresTyping": 1.0,
            "pddlMaxNegationsPerEffect": 2,
            "pddlMinPredicatesPerEffect": 2,
            "torchlight-relevantFacts": -512.0,
            "sasCenamorCGSumOfEdgeWeights": 386880.0,
            "sasCenamorCGRatioNumHighLevelToTotalVariables": 0.670103092784,
            "MpSAT-DIAMETER-entropy": -0.000000000,
            "pddlMeanParamsPerPredicate": 2.0,
            "pddlMinNegationsPerEffect": 1,
            "MpSAT-cluster-coeff-mean": -1.000000000,
            "sasTranslatorOperators": 98208,
            "MpSAT-cl-size-q10": 0.000000000,
            "MpSAT-SP-unconstraint-q10": 0.030700115,
            "pddlRequiresPreferences": 0.0,
            "MpSAT-POSNEG-RATIO-CLAUSE-max": 1.000000000,
            "sasFileMinEffectsPerOperator": 1,
            "sasOperatorsRemoved": 0,
            "meta-success-sas": 1,
            "sasPreprocessingDeemedPolytimeSolvable": 0,
            "torchlight-reachabilityFacts": -512.0,
            "sasInitialInvariantCandidates": 12,
            "MpSAT-cl-size-min": 0.000000000,
            "sasTranslatorDerivedVariables": 0,
            "MpSAT-gsat_FirstLocalMinStep_Median": 0.000000000,
            "fdProbingRatioGoalLandmarksOverInitialLandmarks": -512.0,
            "sasCenamorCGMeanIncomingEdgesPerHighLevelVariable": 32.0,
            "sasCenamorDTGMeanOutgoingEdgeWeightSumPerVertex": 9.56136820926,
            "meta-success-lpg-probing": 0,
            "meta-time-MpSAT-Pre-featuretime": 19.580000000,
            "MpSAT-CG-min": -1.000000000,
            "fdProbingInitialGValue": -512.0,
            "MpSAT-DIAMETER-mean": 14.000000000,
            "fdProbingGoalLandmarks": -512.0,
            "MpSAT-saps_FirstLocalMinStep_Q.10": 0.000000000,
            "meta-success-fd-probing": 0,
            "sasFileNumAxioms": 0,
            "MpSAT-reducedClauses": 3.520169685,
            "meta-success-torchlight": 0,
            "sasCenamorNumHighLevelVariables": 65,
            "lpgProbingNumOps": -512.0,
            "pddlRequiresConstraints": 0.0,
            "sasCenamorDTGMaxOutgoingEdgesPerVertex": 1690,
            "pddlNumPredicates": 8,
            "pddlNumGoals": 65,
            "sasCenamorDTGTotalNumberOfEdges": 194928.0,
            "sasCenamorCGMeanIncomingEdgesPerVariable": 32.3298969072,
            "sasFinalQueueLength": 144305,
            "MpSAT-cl-num-mean": 0.000000000,
            "sasPreprocessingPercentageAxiomRulesDeemedNecessary": -512.0,
            "pddlRequiresADL": 0.0,
            "sasTotalQueuePushes": 334857,
            "pddlMeanPredicatesPerPrecondition": 3.5,
            "sasFileRatioGoalPairsOverNumVariables": 0.670103092784,
            "MpSAT-VCG-VAR-coeff-variation": 4.136527235,
            "meta-time-MpSAT-ls-gsat-featuretime": 3.410000000,
            "pddlNumInitialConditions": 1553,
            "MpSAT-POSNEG-RATIO-CLAUSE-coeff-variation": 1.227776535,
            "MpSAT-BINARY+": 0.988727887,
            "torchlight-exitDistanceMean": -512.0,
            "MpSAT-reducedVars": 4.823768689,
            "sasPreprocessingTaskSize": 589419,
            "pddlNumObjects": 130,
            "sasCenamorDTGMaxOutgoingEdgeWeightSumPerVertex": 948.0,
            "pddlRequiresObjectFluents": 0.0,
            "sasCenamorCGMeanIncomingEdgeWeightSumPerVariable": 3988.45360825,
            "sasImpliedEffectsRemoved": 0,
            "meta-time-MpSAT-Basic-featuretime": 0.360000000,
            "MpSAT-cluster-coeff-max": 0.000000000,
            "MpSAT-lobjois-mean-depth-over-vars": 0.400328798,
            "sasCenamorCGStddevIncomingEdgeWeightSumPerVariable": 4243.93354787,
            "MpSAT-POSNEG-RATIO-VAR-stdev": 0.180979187,
            "fdProbingNumEdges": -512.0,
            "MpSAT-CG-mean": -1.000000000,
            "lpgProbingNumActions": -512.0,
            "MpSAT-saps_BestAvgImprovement_Mean": 49.435000000,
            "fdProbingFinalHeuristicGValue": -512.0,
            "sasRules": 46,
            "MpSAT-saps_FirstLocalMinStep_CoeffVariance": 0.000000000,
            "MpSAT-gsat_BestAvgImprovement_Mean": 8.533920000,
            "sasCenamorDTGStddevOutgoingEdgesPerVertex": 113.702184452,
            "sasTranslatorMutexGroups": 97,
            "sasPreprocessingPercentageVariablesDeemedNecessary": 1.0,
            "MpSAT-SP-bias-coeff-variation": 0.241569466,
            "MpSAT-VCG-VAR-entropy": 1.612222563,
            "sasFileMeanEffectsPerOperator": 1.98484848485,
            "MpSAT-SP-bias-q25": 0.652121710,
            "MpSAT-nclauses": 2461739.000000000,
            "sasCenamorDTGMeanOutgoingEdgesPerVertex": 43.5788061704,
            "pddlRequiresSafetyConstraints": 0.0,
            "sasFileNumVariables": 97,
            "MpSAT-VG-mean": 0.000303980,
            "MpSAT-cl-size-q75": 0.000000000,
            "MpSAT-horn-clauses-fraction": 0.988716919,
            "MpSAT-SP-unconstraint-q75": 0.243826123,
            "pddlRequiresActionCosts": 1.0,
            "sasCenamorCGMeanOutgoingEdgeWeightSumPerVariable": 3988.45360825,
            "MpSAT-DIAMETER-max": 14.000000000,
            "sasFileMaxEffectsPerOperator": 2,
            "MpSAT-gsat_BestSolution_Mean": 214408.000000000,
            "pddlMarksTotalNumActions": 6,
            "sasFileMinVariableDomainSize": 5,
            "pddlNumTypes": 5,
            "pddlMaxParamsPerPredicate": 2,
            "torchlight-hardActionTemplates": -512.0,
            "MpSAT-SP-bias-mean": 0.800235375,
            "pddlRequiresDerivedPredicates": 0.0,
            "lpgProbingNumMutex": -512.0,
            "meta-time-fd-probing": 3.19628000259,
            "MpSAT-cl-num-min": 0.000000000
        }
    }
}
