{
    "instance_features": {
        "./external-assets/problem-instances/planning-instances/ipc-2004-deterministic/optical-telegraphs-derived-adl/problems/ipc-2004-deterministic-optical-telegraphs-derived-adl-P35_opt36.pddl": {
            "MpSAT-gsat_FirstLocalMinStep_CoeffVariance": 0.005400010,
            "MpSAT-VCG-VAR-max": 0.000987636,
            "sasCenamorCGMaxIncomingEdgesPerVariable": 515,
            "MpSAT-DIAMETER-coeff-variation": 0.000000000,
            "sasTranslatorVariables": 2233,
            "MpSAT-VCG-CLAUSE-min": 0.000094162,
            "MpSAT-HORNY-VAR-max": 0.000895251,
            "pddlNumActions": 11,
            "sasCenamorCGNumEdges": 84420,
            "pddlRequiresDomainAxioms": 0.0,
            "pddlRequiresContinuousEffects": 0.0,
            "MpSAT-SP-bias-q90": 1.000000000,
            "MpSAT-SP-unconstraint-mean": 0.062018091,
            "sasFileVersion": 3,
            "MpSAT-nvarsOrig": 162540.000000000,
            "pddlRequiresNegativePreconditions": 0.0,
            "sasImpliedPreconditionsAdded": 0,
            "sasRelevantAtoms": 19376,
            "pddlMeanNegationsPerEffect": 2.72727272727,
            "pddlNumConstantsAndObjects": 223,
            "sasCenamorCGStddevOutgoingEdgeWeightSumPerVariable": 1784.95812112,
            "MpSAT-cluster-coeff-min": -1.000000000,
            "MpSAT-cl-num-q10": 721.000000000,
            "fdProbingFinalHeuristicNum": -512.0,
            "MpSAT-gsat_FirstLocalMinRatio_CoeffVariance": 0.000292604,
            "MpSAT-saps_FirstLocalMinStep_Mean": 5709.330000000,
            "sasCenamorCGStddevIncomingEdgesPerHighLevelVariable": 0.0,
            "MpSAT-cl-num-q75": 721.000000000,
            "sasCenamorCGRatioSumOfWeightsToTotalEdges": 17.2268656716,
            "MpSAT-VG-max": 0.001190002,
            "sasPreprocessingPercentageOperatorsDeemedNecessary": 1.0,
            "MpSAT-VG-coeff-variation": 1.575744888,
            "MpSAT-CG-max": 0.000000000,
            "MpSAT-cl-size-max": 25.468793343,
            "MpSAT-SP-unconstraint-coeff-variation": 1.629614897,
            "pddlMeanPredicatesPerEffect": 5.0,
            "MpSAT-SP-unconstraint-max": 0.500000000,
            "sasCenamorCGMeanOutgoingEdgesPerVariable": 37.8056426332,
            "MpSAT-cl-num-q25": 721.000000000,
            "MpSAT-SP-unconstraint-min": -0.000000000,
            "pddlNumConstants": 0,
            "meta-time-MpSAT-DIAMETER-featuretime": 2.040000000,
            "sasCenamorDTGMaxIncomingEdgeWeightSumPerVertex": 0.0,
            "MpSAT-TRINARY+": 0.959007613,
            "MpSAT-cluster-coeff-entropy": -0.000000000,
            "sasCenamorCGMaxIncomingEdgeWeightSumPerHighLevelVariable": 1820.0,
            "MpSAT-SP-unconstraint-q50": 0.000000000,
            "MpSAT-cl-size-q50": 25.468793343,
            "MpSAT-SP-bias-q10": 0.602646804,
            "sasUncoveredFacts": 3241,
            "MpSAT-POSNEG-RATIO-VAR-entropy": 3.816138343,
            "MpSAT-POSNEG-RATIO-VAR-min": 0.000000000,
            "MpSAT-VCG-CLAUSE-coeff-variation": 2.954035664,
            "MpSAT-cl-num-q50": 721.000000000,
            "MpSAT-DIAMETER-min": 5.000000000,
            "fdProbingLandmarksPercentageDisjunctive": -512.0,
            "MpSAT-SP-bias-min": 0.005461267,
            "torchlight-successPercentage": -512.0,
            "torchlight-deadEndPercentage": -512.0,
            "meta-time-simple-pddl": 0.046578168869,
            "MpSAT-SP-bias-max": 1.000000000,
            "MpSAT-saps_BestSolution_Mean": 744.000000000,
            "meta-time-MpSAT": 99.3614759445,
            "sasFileNumOperators": 7812,
            "lpgProbingNumFactsIndividual": -512.0,
            "MpSAT-saps_BestSolution_CoeffVariance": 1.294400000,
            "fdProbingLandmarksPercentageConjunctive": -512.0,
            "sasPropositionsRemoved": 2916,
            "pddlRequiresStrips": 0.0,
            "MpSAT-gsat_FirstLocalMinRatio_Mean": 0.994736000,
            "fdProbingFinalStatesEvaluated": -512.0,
            "pddlRequiresDurativeActions": 0.0,
            "sasCenamorDTGTotalNumberOfVertices": 7634.0,
            "meta-time-MpSAT-cl-featuretime": 1.480000000,
            "MpSAT-SP-unconstraint-q25": 0.000000000,
            "sasCenamorCGMaxOutgoingEdgesPerVariable": 162,
            "MpSAT-gsat_BestAvgImprovement_CoeffVariance": 0.149043000,
            "sasFileHasMetric": 0,
            "sasCenamorTotalNumVariables": 2233,
            "MpSAT-POSNEG-RATIO-VAR-mean": 0.522993062,
            "fdProbingLandmarksDiscovered": -512.0,
            "MpSAT-CG-entropy": -512.000000000,
            "sasCenamorCGRatioTotalVariablesToTotalEdges": 0.0264510779436,
            "meta-time-torchlight": 36.535681963,
            "sasCenamorCGStddevOutgoingEdgesPerVariable": 63.1946261528,
            "pddlRatioActionsWithNegativeEffectsOverActions": 0.909090909091,
            "MpSAT-POSNEG-RATIO-CLAUSE-mean": 0.439044924,
            "pddlMaxPredicatesPerEffect": 9,
            "sasFileMeanVariableDomainSize": 3.41871921182,
            "sasFileMeanConditionsPerAxiom": 1.14840499307,
            "meta-success-MpSAT": 1,
            "sasTranslatorFacts": 7634,
            "lpgProbingNumFacts": -512.0,
            "torchlight-reachabilityActions": -512.0,
            "MpSAT-SP-unconstraint-q90": 0.227952521,
            "pddlRequiresFluents": 0.0,
            "sasCenamorDTGStddevIncomingEdgeWeightSumPerVertex": 0.0,
            "sasCenamorCGMaxIncomingEdgesPerHighLevelVariable": 515,
            "sasCenamorCGMeanIncomingEdgeWeightSumPerHighLevelVariable": 1820.0,
            "pddlRequiresExistentialPreconditions": 0.0,
            "MpSAT-saps_FirstLocalMinStep_Median": 8533.000000000,
            "MpSAT-VCG-CLAUSE-entropy": 0.312601118,
            "MpSAT-POSNEG-RATIO-VAR-max": 0.979545455,
            "MpSAT-HORNY-VAR-entropy": 3.684289011,
            "MpSAT-SP-bias-q50": 1.000000000,
            "fdProbingInitialHeuristicNum": -512.0,
            "sasTranslatorTaskSize": 1140952,
            "sasCenamorDTGStddevOutgoingEdgeWeightSumPerVertex": 0.0,
            "sasCenamorDTGMaxIncomingEdgesPerVertex": 7100,
            "MpSAT-nclausesOrig": 10214892.000000000,
            "sasAuxiliaryAtoms": 33873,
            "sasCenamorDTGStddevIncomingEdgesPerVertex": 486.53479795,
            "MpSAT-saps_FirstLocalMinStep_Q.90": 8533.000000000,
            "MpSAT-nvars": 21240.000000000,
            "MpSAT-cl-size-coeff-variation": 0.000000000,
            "sasCenamorCGRatioSumOfWeightsToTotalVariables": 651.272727273,
            "MpSAT-lobjois-log-num-nodes-over-vars": 0.545078928,
            "torchlight-easyActionTemplates": -512.0,
            "pddlHasTypes": 1,
            "pddlRequiresNegation": 0.0,
            "sasFileMinConditionsPerAxiom": 1,
            "pddlMinParamsPerPredicate": 1,
            "sasCenamorDTGMeanIncomingEdgesPerVertex": 76.1735656275,
            "sasFileNumGoalPairs": 72,
            "MpSAT-cluster-coeff-coeff-variation": -0.000000000,
            "MpSAT-SP-bias-q75": 1.000000000,
            "pddlRequiresDurationInequalities": 0.0,
            "meta-time-MpSAT-sp-featuretime": 4.820000000,
            "MpSAT-HORNY-VAR-mean": 0.000089520,
            "MpSAT-VCG-CLAUSE-max": 0.010263653,
            "sasFileMaxConditionsPerAxiom": 108,
            "MpSAT-cl-size-q90": 25.468793343,
            "sasFileMaxPrevailConditionsPerOperator": 2,
            "sasFileMinPrevailConditionsPerOperator": 0,
            "pddlRequiresQuantifiedPreconditions": 0.0,
            "MpSAT-POSNEG-RATIO-CLAUSE-entropy": 0.944585561,
            "sasCenamorCGMaxOutgoingEdgeWeightSumPerVariable": 7892,
            "lpgProbingNumConditionalActions": -512.0,
            "MpSAT-VCG-VAR-min": 0.000006599,
            "pddlNumEqualityInitialConditions": 223,
            "pddlMaxPredicatesPerPrecondition": 9,
            "MpSAT-CG-coeff-variation": -0.000000000,
            "pddlRequiresTimedInitialLiterals": 0.0,
            "MpSAT-cl-size-mean": 25.468793343,
            "sasPreprocessingNumFacts": 7634,
            "torchlight-exitDistanceMin": -512.0,
            "sasPreprocessingDerivedVariables": 721,
            "MpSAT-cl-num-q90": 721.000000000,
            "torchlight-exitDistanceMax": -512.0,
            "MpSAT-cl-num-max": 721.000000000,
            "MpSAT-saps_BestAvgImprovement_CoeffVariance": 0.570306000,
            "meta-time-MpSAT-ls-saps-featuretime": 2.520000000,
            "MpSAT-HORNY-VAR-coeff-variation": 1.563811932,
            "sasFileMaxVariableDomainSize": 32,
            "MpSAT-gsat_FirstLocalMinStep_Q.10": 8400.000000000,
            "MpSAT-VCG-VAR-mean": 0.000118311,
            "pddlRequiresConditionalEffects": 0.0,
            "sasCenamorCGStddevIncomingEdgeWeightSumPerHighLevelVariable": 0.0,
            "fdProbingPercentageImprovementNum": -512.0,
            "MpSAT-cl-num-coeff-variation": 0.000000000,
            "MpSAT-POSNEG-RATIO-CLAUSE-min": 0.000000000,
            "sasCenamorDTGMeanIncomingEdgeWeightSumPerVertex": 0.0,
            "MpSAT-cl-size-q25": 25.468793343,
            "pddlRequiresEquality": 1.0,
            "meta-time-MpSAT-CG-featuretime": 20.060000000,
            "MpSAT-saps_FirstLocalMinRatio_CoeffVariance": 0.008821490,
            "sasPreprocessingPercentageMutexGroupsDeemedNecessary": 0.0,
            "sasCenamorCGMaxIncomingEdgeWeightSumPerVariable": 17891,
            "fdProbingReasonableOrdersRemoved": -512.0,
            "fdProbingInitialHeuristicDen": -512.0,
            "MpSAT-UNARY": 0.000000000,
            "meta-success-simple-pddl": 1,
            "meta-time-MpSAT-KLB-featuretime": 1.440000000,
            "MpSAT-VCG-CLAUSE-mean": 0.000118311,
            "fdProbingFinalHeuristicDen": -512.0,
            "fdProbingInitialLandmarks": -512.0,
            "pddlRequiresNumericFluents": 0.0,
            "sasCenamorCGStddevIncomingEdgesPerVariable": 124.756392817,
            "meta-time-lpg-probing": 0.200040817261,
            "sasFileMeanPrevailConditionsPerOperator": 1.23502304147,
            "meta-time-MpSAT-lobjois-featuretime": 2.030000000,
            "MpSAT-gsat_FirstLocalMinStep_Mean": 8483.000000000,
            "pddlRequiresDisjunctivePreconditions": 0.0,
            "MpSAT-vars-clauses-ratio": 0.023360118,
            "sasTranslatorTotalMutexGroupsSize": 5220,
            "MpSAT-VG-min": 0.000004399,
            "MpSAT-HORNY-VAR-min": 0.000002200,
            "MpSAT-gsat_BestSolution_CoeffVariance": 0.044953800,
            "sasEffectConditionsSimplified": 51840,
            "pddlNumFunctionAssignmentsInInitialConditions": 0,
            "MpSAT-saps_FirstLocalMinRatio_Mean": 0.998638000,
            "pddlRequiresUniversalPreconditions": 0.0,
            "MpSAT-gsat_FirstLocalMinStep_Q.90": 8500.000000000,
            "sasCenamorDTGSumOfEdgeWeights": 0.0,
            "pddlMinPredicatesPerPrecondition": 3,
            "meta-time-sas": 90.8561820984,
            "pddlRequiresTyping": 1.0,
            "pddlMaxNegationsPerEffect": 4,
            "pddlMinPredicatesPerEffect": 1,
            "torchlight-relevantFacts": -512.0,
            "sasCenamorCGSumOfEdgeWeights": 1454292.0,
            "sasCenamorCGRatioNumHighLevelToTotalVariables": 0.0322436184505,
            "MpSAT-DIAMETER-entropy": -0.000000000,
            "pddlMeanParamsPerPredicate": 1.96551724138,
            "pddlMinNegationsPerEffect": 0,
            "MpSAT-cluster-coeff-mean": -1.000000000,
            "sasTranslatorOperators": 7812,
            "MpSAT-cl-size-q10": 25.468793343,
            "MpSAT-SP-unconstraint-q10": 0.000000000,
            "pddlRequiresPreferences": 0.0,
            "MpSAT-POSNEG-RATIO-CLAUSE-max": 1.000000000,
            "sasFileMinEffectsPerOperator": 1,
            "sasOperatorsRemoved": 216,
            "meta-success-sas": 1,
            "sasPreprocessingDeemedPolytimeSolvable": 0,
            "torchlight-reachabilityFacts": -512.0,
            "sasInitialInvariantCandidates": 41,
            "MpSAT-cl-size-min": 25.468793343,
            "sasTranslatorDerivedVariables": 721,
            "MpSAT-gsat_FirstLocalMinStep_Median": 8487.500000000,
            "fdProbingRatioGoalLandmarksOverInitialLandmarks": -512.0,
            "sasCenamorCGMeanIncomingEdgesPerHighLevelVariable": 515.0,
            "sasCenamorDTGMeanOutgoingEdgeWeightSumPerVertex": 0.0,
            "meta-success-lpg-probing": 0,
            "meta-time-MpSAT-Pre-featuretime": 21.890000000,
            "MpSAT-CG-min": -1.000000000,
            "fdProbingInitialGValue": -512.0,
            "MpSAT-DIAMETER-mean": 5.000000000,
            "fdProbingGoalLandmarks": -512.0,
            "MpSAT-saps_FirstLocalMinStep_Q.10": 0.000000000,
            "meta-success-fd-probing": 0,
            "sasFileNumAxioms": 721,
            "MpSAT-reducedClauses": 10.234514024,
            "meta-success-torchlight": 0,
            "sasCenamorNumHighLevelVariables": 72,
            "lpgProbingNumOps": -512.0,
            "pddlRequiresConstraints": 0.0,
            "sasCenamorDTGMaxOutgoingEdgesPerVertex": 720,
            "pddlNumPredicates": 29,
            "pddlNumGoals": 72,
            "sasCenamorDTGTotalNumberOfEdges": 581509.0,
            "sasCenamorCGMeanIncomingEdgesPerVariable": 37.8056426332,
            "sasFinalQueueLength": 53249,
            "MpSAT-cl-num-mean": 721.000000000,
            "sasPreprocessingPercentageAxiomRulesDeemedNecessary": 1.0,
            "pddlRequiresADL": 0.0,
            "sasTotalQueuePushes": 67324,
            "pddlMeanPredicatesPerPrecondition": 5.90909090909,
            "sasFileRatioGoalPairsOverNumVariables": 0.0322436184505,
            "MpSAT-VCG-VAR-coeff-variation": 1.581844577,
            "meta-time-MpSAT-ls-gsat-featuretime": 2.540000000,
            "pddlNumInitialConditions": 1641,
            "MpSAT-POSNEG-RATIO-CLAUSE-coeff-variation": 1.109502083,
            "MpSAT-BINARY+": 0.949371015,
            "torchlight-exitDistanceMean": -512.0,
            "MpSAT-reducedVars": 6.652542373,
            "sasPreprocessingTaskSize": 1135732,
            "pddlNumObjects": 223,
            "sasCenamorDTGMaxOutgoingEdgeWeightSumPerVertex": 0.0,
            "pddlRequiresObjectFluents": 0.0,
            "sasCenamorCGMeanIncomingEdgeWeightSumPerVariable": 651.272727273,
            "sasImpliedEffectsRemoved": 2160,
            "meta-time-MpSAT-Basic-featuretime": 0.110000000,
            "MpSAT-cluster-coeff-max": 0.000000000,
            "MpSAT-lobjois-mean-depth-over-vars": 0.230378490,
            "sasCenamorCGStddevIncomingEdgeWeightSumPerVariable": 3163.67316028,
            "MpSAT-POSNEG-RATIO-VAR-stdev": 0.334935818,
            "fdProbingNumEdges": -512.0,
            "MpSAT-CG-mean": -1.000000000,
            "lpgProbingNumActions": -512.0,
            "MpSAT-saps_BestAvgImprovement_Mean": 15.396200000,
            "fdProbingFinalHeuristicGValue": -512.0,
            "sasRules": 144,
            "MpSAT-saps_FirstLocalMinStep_CoeffVariance": 0.866042000,
            "MpSAT-gsat_BestAvgImprovement_Mean": 5.116260000,
            "sasCenamorDTGStddevOutgoingEdgesPerVertex": 152.741821372,
            "sasTranslatorMutexGroups": 432,
            "sasPreprocessingPercentageVariablesDeemedNecessary": 1.0,
            "MpSAT-SP-bias-coeff-variation": 0.229223519,
            "MpSAT-VCG-VAR-entropy": 4.027302622,
            "sasFileMeanEffectsPerOperator": 74.4193548387,
            "MpSAT-SP-bias-q25": 0.911110103,
            "MpSAT-nclauses": 909242.000000000,
            "sasCenamorDTGMeanOutgoingEdgesPerVertex": 76.1735656275,
            "pddlRequiresSafetyConstraints": 0.0,
            "sasFileNumVariables": 2233,
            "MpSAT-VG-mean": 0.000148319,
            "MpSAT-cl-size-q75": 25.468793343,
            "MpSAT-horn-clauses-fraction": 0.950061700,
            "MpSAT-SP-unconstraint-q75": 0.120348360,
            "pddlRequiresActionCosts": 0.0,
            "sasCenamorCGMeanOutgoingEdgeWeightSumPerVariable": 651.272727273,
            "MpSAT-DIAMETER-max": 5.000000000,
            "sasFileMaxEffectsPerOperator": 785,
            "MpSAT-gsat_BestSolution_Mean": 457.333000000,
            "pddlMarksTotalNumActions": 11,
            "sasFileMinVariableDomainSize": 2,
            "pddlNumTypes": 9,
            "pddlMaxParamsPerPredicate": 4,
            "torchlight-hardActionTemplates": -512.0,
            "MpSAT-SP-bias-mean": 0.898078302,
            "pddlRequiresDerivedPredicates": 0.0,
            "lpgProbingNumMutex": -512.0,
            "meta-time-fd-probing": 3.21088790894,
            "MpSAT-cl-num-min": 721.000000000
        }
    }
}
